{
  "lastUpdated": "2026-02-25T23:20:07.148071Z",
  "upcomingMatches": [
    {
      "id": "b9ade3f715e4c344543f672014bc2188",
      "commenceTime": "2026-02-27T20:00:00Z",
      "homeTeam": "Wolves",
      "awayTeam": "Aston Villa",
      "h2hOdds": {
        "bookmaker": "DraftKings",
        "home": 3.85,
        "draw": 3.75,
        "away": 1.87,
        "impliedProbHome": 0.26,
        "impliedProbDraw": 0.267,
        "impliedProbAway": 0.535
      },
      "spread": {
        "homePoint": 0.5,
        "awayPoint": -0.5,
        "byBookmaker": {
          "mybookieag": 0.5
        }
      },
      "kalshiOdds": {
        "homeWinProb": 0.2277,
        "drawProb": 0.2574,
        "awayWinProb": 0.5149
      }
    },
    {
      "id": "621cff11a60f850184fc515327f29a11",
      "commenceTime": "2026-02-28T12:30:00Z",
      "homeTeam": "Bournemouth",
      "awayTeam": "Sunderland",
      "h2hOdds": {
        "bookmaker": "DraftKings",
        "home": 1.8,
        "draw": 3.8,
        "away": 4.2,
        "impliedProbHome": 0.556,
        "impliedProbDraw": 0.263,
        "impliedProbAway": 0.238
      },
      "spread": {
        "homePoint": -0.5,
        "awayPoint": 0.5,
        "byBookmaker": {
          "mybookieag": -0.5
        }
      },
      "kalshiOdds": {
        "homeWinProb": 0.5243,
        "drawProb": 0.2524,
        "awayWinProb": 0.2233
      }
    },
    {
      "id": "c31face07c72bd0418f18dc032764cea",
      "commenceTime": "2026-02-28T15:00:00Z",
      "homeTeam": "Burnley",
      "awayTeam": "Brentford",
      "h2hOdds": {
        "bookmaker": "DraftKings",
        "home": 4.1,
        "draw": 3.8,
        "away": 1.8,
        "impliedProbHome": 0.244,
        "impliedProbDraw": 0.263,
        "impliedProbAway": 0.556
      },
      "spread": {
        "homePoint": 0.5,
        "awayPoint": -0.5,
        "byBookmaker": {
          "mybookieag": 0.5
        }
      },
      "kalshiOdds": {
        "homeWinProb": 0.2115,
        "drawProb": 0.25,
        "awayWinProb": 0.5385
      }
    },
    {
      "id": "5eeaa47bfb416d8b2a5f25cf16731cb2",
      "commenceTime": "2026-02-28T15:00:00Z",
      "homeTeam": "Newcastle",
      "awayTeam": "Everton",
      "h2hOdds": {
        "bookmaker": "DraftKings",
        "home": 1.77,
        "draw": 3.75,
        "away": 4.3,
        "impliedProbHome": 0.565,
        "impliedProbDraw": 0.267,
        "impliedProbAway": 0.233
      },
      "spread": {
        "homePoint": -0.5,
        "awayPoint": 0.5,
        "byBookmaker": {
          "mybookieag": -0.5
        }
      },
      "kalshiOdds": {
        "homeWinProb": 0.549,
        "drawProb": 0.2451,
        "awayWinProb": 0.2059
      }
    },
    {
      "id": "466f3df43a6647947e4fb9cab6657d80",
      "commenceTime": "2026-02-28T15:00:00Z",
      "homeTeam": "Liverpool",
      "awayTeam": "West Ham",
      "h2hOdds": {
        "bookmaker": "DraftKings",
        "home": 1.38,
        "draw": 5.25,
        "away": 7.0,
        "impliedProbHome": 0.725,
        "impliedProbDraw": 0.19,
        "impliedProbAway": 0.143
      },
      "spread": {
        "homePoint": -1.5,
        "awayPoint": 1.5,
        "byBookmaker": {
          "mybookieag": -1.5
        }
      },
      "kalshiOdds": {
        "homeWinProb": 0.6893,
        "drawProb": 0.1845,
        "awayWinProb": 0.1262
      }
    },
    {
      "id": "300862b165c77b6fe6c3fccf717aba1e",
      "commenceTime": "2026-02-28T17:30:00Z",
      "homeTeam": "Leeds",
      "awayTeam": "Man City",
      "h2hOdds": {
        "bookmaker": "DraftKings",
        "home": 4.8,
        "draw": 4.3,
        "away": 1.61,
        "impliedProbHome": 0.208,
        "impliedProbDraw": 0.233,
        "impliedProbAway": 0.621
      },
      "spread": {
        "homePoint": 0.5,
        "awayPoint": -0.5,
        "byBookmaker": {
          "mybookieag": 0.5
        }
      },
      "kalshiOdds": {
        "homeWinProb": 0.1748,
        "drawProb": 0.2233,
        "awayWinProb": 0.6019
      }
    },
    {
      "id": "b0e5c780eac6e73974f5d023b9a7f17b",
      "commenceTime": "2026-03-01T14:00:00Z",
      "homeTeam": "Brighton",
      "awayTeam": "Nott'm Forest",
      "h2hOdds": {
        "bookmaker": "DraftKings",
        "home": 2.1,
        "draw": 3.5,
        "away": 3.35,
        "impliedProbHome": 0.476,
        "impliedProbDraw": 0.286,
        "impliedProbAway": 0.299
      },
      "spread": {
        "homePoint": -0.5,
        "awayPoint": 0.5,
        "byBookmaker": {
          "mybookieag": -0.5
        }
      },
      "kalshiOdds": {
        "homeWinProb": 0.4563,
        "drawProb": 0.2718,
        "awayWinProb": 0.2718
      }
    },
    {
      "id": "17717f1dec1142342e08b89ec57dafa8",
      "commenceTime": "2026-03-01T14:00:00Z",
      "homeTeam": "Man United",
      "awayTeam": "Crystal Palace",
      "h2hOdds": {
        "bookmaker": "DraftKings",
        "home": 1.59,
        "draw": 4.2,
        "away": 5.0,
        "impliedProbHome": 0.629,
        "impliedProbDraw": 0.238,
        "impliedProbAway": 0.2
      },
      "spread": {
        "homePoint": -0.5,
        "awayPoint": 0.5,
        "byBookmaker": {
          "mybookieag": -0.5
        }
      },
      "kalshiOdds": {
        "homeWinProb": 0.6117,
        "drawProb": 0.2233,
        "awayWinProb": 0.165
      }
    },
    {
      "id": "c9a6fecd9a75e1db00f4a2aa82e0b69e",
      "commenceTime": "2026-03-01T14:00:00Z",
      "homeTeam": "Fulham",
      "awayTeam": "Tottenham",
      "h2hOdds": {
        "bookmaker": "DraftKings",
        "home": 2.25,
        "draw": 3.4,
        "away": 3.0,
        "impliedProbHome": 0.444,
        "impliedProbDraw": 0.294,
        "impliedProbAway": 0.333
      },
      "spread": {
        "homePoint": -0.5,
        "awayPoint": 0.5,
        "byBookmaker": {
          "mybookieag": -0.5
        }
      },
      "kalshiOdds": {
        "homeWinProb": 0.4466,
        "drawProb": 0.2718,
        "awayWinProb": 0.2816
      }
    },
    {
      "id": "9471be41334d79e0e85fda9feb065bfa",
      "commenceTime": "2026-03-01T16:30:00Z",
      "homeTeam": "Arsenal",
      "awayTeam": "Chelsea",
      "h2hOdds": {
        "bookmaker": "DraftKings",
        "home": 1.67,
        "draw": 3.95,
        "away": 4.9,
        "impliedProbHome": 0.599,
        "impliedProbDraw": 0.253,
        "impliedProbAway": 0.204
      },
      "spread": {
        "homePoint": -0.5,
        "awayPoint": 0.5,
        "byBookmaker": {
          "mybookieag": -0.5
        }
      },
      "kalshiOdds": {
        "homeWinProb": 0.5865,
        "drawProb": 0.2308,
        "awayWinProb": 0.1827
      }
    }
  ],
  "bookmakers": [
    "backfill",
    "matchbook",
    "mybookieag"
  ],
  "totalMatches": 10
}